iwutil/__init__.py
iwutil/_version.py
iwutil/random.py
iwutil/save.py
iwutil-0.3.10.dist-info/METADATA
iwutil-0.3.10.dist-info/WHEEL
iwutil-0.3.10.dist-info/licenses/LICENSE.md
iwutil-0.3.10.dist-info/RECORD
