Metadata-Version: 2.4
Name: iwutil
Version: 0.3.10
Summary: Public utility functions for Ionworks code.
Project-URL: Homepage, https://github.com/ionworks/iwutil
Project-URL: Issues, https://github.com/ionworks/iwutil/issues
Author-email: Ionworks Technologies Inc <info@ionworks.com>
License: Copyright (c) 2024, Ionworks Technologies Inc.
License-File: LICENSE.md
Requires-Python: >=3.10
Requires-Dist: matplotlib
Requires-Dist: numpy
Requires-Dist: pandas[feather,parquet]
Provides-Extra: dev
Requires-Dist: myst-parser; extra == 'dev'
Requires-Dist: pytest; extra == 'dev'
Requires-Dist: sphinx; extra == 'dev'
Requires-Dist: sphinx-rtd-theme; extra == 'dev'
Provides-Extra: polars
Requires-Dist: polars; extra == 'polars'
